{"nodes": [{"id": "MainActivity", "label": "MainActivity", "file_type": "code", "source_file": "app/src/main/AndroidManifest.xml", "source_location": "AndroidManifest.xml:26", "source_url": null, "captured_at": null, "author": null, "contributor": null}, {"id": "FieldStackApp", "label": "FieldStackApp", "file_type": "code", "source_file": "app/src/main/AndroidManifest.xml", "source_location": "AndroidManifest.xml:16", "source_url": null, "captured_at": null, "author": null, "contributor": null}, {"id": "AndroidManifest", "label": "AndroidManifest", "file_type": "code", "source_file": "app/src/main/AndroidManifest.xml", "source_location": "AndroidManifest.xml:1", "source_url": null, "captured_at": null, "author": null, "contributor": null}], "edges": [{"source": "AndroidManifest", "target": "MainActivity", "relation": "references", "confidence": "EXTRACTED", "confidence_score": 1.0, "source_file": "app/src/main/AndroidManifest.xml", "source_location": "AndroidManifest.xml:26", "weight": 0.5}, {"source": "AndroidManifest", "target": "FieldStackApp", "relation": "references", "confidence": "EXTRACTED", "confidence_score": 1.0, "source_file": "app/src/main/AndroidManifest.xml", "source_location": "AndroidManifest.xml:16", "weight": 0.5}], "hyperedges": []}